ramachandran/__init__.py
ramachandran/download.py
ramachandran/geometry.py
ramachandran/io.py
ramachandran/plot.py
ramachandran/statistics.py
ramachandran/torsion.py
ramachandran/data/gaussian_density.npz
ramachandran/data/probability.npz
ramachandran-0.0.2.data/scripts/ramachandran-plot
ramachandran-0.0.2.dist-info/LICENSE.md
ramachandran-0.0.2.dist-info/METADATA
ramachandran-0.0.2.dist-info/WHEEL
ramachandran-0.0.2.dist-info/top_level.txt
ramachandran-0.0.2.dist-info/RECORD
