Metadata-Version: 2.1
Name: ramachandran
Version: 0.0.2
Summary: Generating Ramachandran plot and statistics.
Home-page: https://github.com/leimao/Ramachandran
Author: Lei Mao
Author-email: dukeleimao@gmail.com
License: UNKNOWN
Platform: UNKNOWN
Classifier: Programming Language :: Python :: 3
Classifier: License :: OSI Approved :: MIT License
Classifier: Operating System :: OS Independent
Requires-Python: >=3.8
